trans_analysis/__init__.py
trans_analysis/__main__.py
trans_analysis/analyzer.py
trans_analysis_super_kolya-0.1.1.dist-info/METADATA
trans_analysis_super_kolya-0.1.1.dist-info/WHEEL
trans_analysis_super_kolya-0.1.1.dist-info/entry_points.txt
trans_analysis_super_kolya-0.1.1.dist-info/top_level.txt
trans_analysis_super_kolya-0.1.1.dist-info/RECORD
