Metadata-Version: 2.1
Name: trans_analysis_super_kolya
Version: 0.1.1
Summary: Пакет для анализа финансовых транзакций
Author-email: Nikolai <kolaleuhin@gmail.com>
Requires-Dist: pandas
